stwcs/__init__.py
stwcs/version.py
stwcs/distortion/__init__.py
stwcs/distortion/coeff_converter.py
stwcs/distortion/models.py
stwcs/distortion/mutil.py
stwcs/distortion/utils.py
stwcs/gui/__init__.py
stwcs/gui/apply_headerlet.help
stwcs/gui/apply_headerlet.py
stwcs/gui/archive_headerlet.py
stwcs/gui/attach_headerlet.py
stwcs/gui/delete_headerlet.py
stwcs/gui/extract_headerlet.py
stwcs/gui/headerlet_summary.py
stwcs/gui/restore_headerlet.help
stwcs/gui/restore_headerlet.py
stwcs/gui/updatewcs.py
stwcs/gui/write_headerlet.py
stwcs/tests/__init__.py
stwcs/tests/test_altwcs.py
stwcs/tests/test_astrometrydb.py
stwcs/tests/test_headerlet.py
stwcs/tests/test_hstwcs.py
stwcs/tests/test_updatewcs.py
stwcs/tests/data/__init__.py
stwcs/updatewcs/__init__.py
stwcs/updatewcs/apply_corrections.py
stwcs/updatewcs/astrometry_utils.py
stwcs/updatewcs/corrections.py
stwcs/updatewcs/det2im.py
stwcs/updatewcs/makewcs.py
stwcs/updatewcs/npol.py
stwcs/updatewcs/updatehdr.py
stwcs/updatewcs/utils.py
stwcs/updatewcs/wfpc2_dgeo.py
stwcs/wcsutil/__init__.py
stwcs/wcsutil/altwcs.py
stwcs/wcsutil/convertwcs.py
stwcs/wcsutil/getinput.py
stwcs/wcsutil/headerlet.py
stwcs/wcsutil/hstwcs.py
stwcs/wcsutil/instruments.py
stwcs/wcsutil/mappings.py
stwcs/wcsutil/mosaic.py
stwcs/wcsutil/wcscorr.py
stwcs/wcsutil/wcsdiff.py
stwcs-1.7.5.dist-info/METADATA
stwcs-1.7.5.dist-info/WHEEL
stwcs-1.7.5.dist-info/top_level.txt
stwcs-1.7.5.dist-info/RECORD
