Metadata-Version: 2.4
Name: stwcs
Version: 1.7.5
Summary: Computes the WCS of HST images.
Author-email: STScI <help@stsci.edu>
Project-URL: Repository, https://github.com/spacetelescope/stwcs.git
Project-URL: Documentation, https://stwcs.readthedocs.io
Classifier: Intended Audience :: Science/Research
Classifier: License :: OSI Approved :: BSD License
Classifier: Operating System :: OS Independent
Classifier: Programming Language :: Python
Classifier: Topic :: Scientific/Engineering :: Astronomy
Classifier: Topic :: Software Development :: Libraries :: Python Modules
Requires-Dist: astropy>=6.0
Requires-Dist: numpy>=2.0
Requires-Dist: stsci.tools>=3.6
Requires-Dist: requests
Requires-Dist: lxml
Provides-Extra: docs
Requires-Dist: sphinx; extra == "docs"
Requires-Dist: sphinx-automodapi; extra == "docs"
Requires-Dist: sphinx-rtd-theme; extra == "docs"
Provides-Extra: test
Requires-Dist: pytest; extra == "test"
